pyproton/__init__.py
pyproton/vpn.py
pyproton-0.0.5.dist-info/LICENSE
pyproton-0.0.5.dist-info/METADATA
pyproton-0.0.5.dist-info/WHEEL
pyproton-0.0.5.dist-info/top_level.txt
pyproton-0.0.5.dist-info/RECORD
