Metadata-Version: 2.1
Name: pyproton
Version: 0.0.5
Summary: Minimal wrapper implementation of the linux protonvpn-cli
Home-page: https://github.com/aastopher/pyproton
Author: Aaron Stopher
Project-URL: Bug Tracker, https://github.com/aastopher/pyproton/issues
Keywords: vpn,proton vpn,proton,wrapper,cli
Classifier: Programming Language :: Python :: 3
Classifier: License :: OSI Approved :: MIT License
Classifier: Operating System :: POSIX :: Linux
Requires-Python: >=3.9
License-File: LICENSE
